MANIFEST.in
setup.py
Phial_Toolset.egg-info/PKG-INFO
Phial_Toolset.egg-info/SOURCES.txt
Phial_Toolset.egg-info/dependency_links.txt
Phial_Toolset.egg-info/top_level.txt
phial/__init__.py
phial/g.py
phial/phial-init
phial/phial.py
phial/assets/static/phial/css/foundation.min.css
phial/assets/static/phial/img/.gitkeep
phial/assets/static/phial/img/favicon.ico
phial/assets/static/phial/img/phial.png
phial/assets/static/phial/js/vendor/modernizr.js
phial/assets/templates/phial/default_debug_404.html
phial/assets/templates/phial/default_welcome.html
phial/flask_tools/__init__.py
phial/flask_tools/lazy_text.py
phial/flask_tools/url_map_regex_converter.py
phial/flask_tools/callback/__init__.py
phial/flask_tools/callback/after_peewee_close.py
phial/flask_tools/callback/before_i18n_set_user_language.py
phial/flask_tools/callback/before_peewee_connect.py
phial/flask_tools/callback/before_url_remove_trailing_slash.py
phial/flask_tools/session/__init__.py
phial/flask_tools/session/session_redis.py
phial/jinja_tools/__init__.py
phial/jinja_tools/get_translation_engine.py
phial/jinja_tools/ext/__init__.py
phial/jinja_tools/ext/jinja2datetime.py
phial/jinja_tools/ext/jinja2htmlcompress.py
phial/peewee_tools/__init__.py
phial/peewee_tools/base_model.py
phial/peewee_tools/database_init.py
phial/phial_management/__init__.py
phial/phial_management/server.py
phial/phial_management/shell.py
phial/phial_management/syncdb.py