Metadata-Version: 1.1
Name: Phial-Toolset
Version: 1.0.1
Summary: Non-intrusive toolset to easily use Flask/Peewee/Celery
Home-page: https://github.com/0xbaadf00d/phial
Author: Thibault Meyer
Author-email: meyer.thibault@gmail.com
License: The MIT License (MIT)
Platform: UNKNOWN
Classifier: Development Status :: 5 - Production/Stable
Classifier: Environment :: Web Environment
Classifier: Intended Audience :: Developers
Classifier: License :: OSI Approved :: MIT License
Classifier: Operating System :: OS Independent
Classifier: Programming Language :: Python
Classifier: Programming Language :: Python :: 2.7
Classifier: Programming Language :: Python :: 3
Classifier: Programming Language :: Python :: 3.2
Classifier: Programming Language :: Python :: 3.3
Classifier: Programming Language :: Python :: 3.4
Classifier: Topic :: Internet :: WWW/HTTP
Classifier: Topic :: Software Development :: Libraries :: Application Frameworks
Classifier: Topic :: Software Development :: Libraries :: Python Modules
Requires: flask
Requires: ipython
Requires: Jinja2
